README
setup.py
nimbstor/__init__.py
nimbstor/combine_backend.py
nimbstor/directory_backend.py
nimbstor/imap_backend.py
nimbstor/nimbtar
nimbstor/optimized.pyx
nimbstor/sftp_backend.py
nimbstor/stor.py
nimbstor/tar.py
nimbstor/tests.py
nimbstor/webdav_backend.py
nimbstor.egg-info/PKG-INFO
nimbstor.egg-info/SOURCES.txt
nimbstor.egg-info/dependency_links.txt
nimbstor.egg-info/not-zip-safe
nimbstor.egg-info/top_level.txt