Metadata-Version: 1.0
Name: nimbstor
Version: 1.0.1
Summary: Store incrementally, compressed and encrypted data failsafe in filesystems, sFTP, WebDAV, IMAP or other backends.
Home-page: http://pypi.python.org/pypi/nimbstor
Author: Oleksandr Kozachuk
Author-email: ddeus.pypi@mailnull.com
License: WTFPL
Platform: UNKNOWN
Classifier: Development Status :: 4 - Beta
Classifier: Environment :: Console
Classifier: Intended Audience :: End Users/Desktop
Classifier: Intended Audience :: System Administrators
Classifier: Operating System :: Unix
Classifier: Operating System :: POSIX
Classifier: Programming Language :: Python :: 2.6
Classifier: Programming Language :: Python :: 2.7
Classifier: Topic :: System :: Archiving
Classifier: Topic :: System :: Archiving :: Backup
Classifier: Topic :: System :: Archiving :: Compression
Classifier: Topic :: System :: Archiving :: Mirroring
Classifier: Topic :: System :: Archiving :: Packaging
Classifier: Topic :: Utilities
